[{"name":"ringieradsdk","description":null,"location":"index.html","searchKeys":["ringieradsdk"]},{"name":"ch.iagentur.ringieradsdk","description":null,"location":"ringieradsdk/ch.iagentur.ringieradsdk/index.html","searchKeys":["ch.iagentur.ringieradsdk"]},{"name":"RingierAd","description":null,"location":"ringieradsdk/ch.iagentur.ringieradsdk/-ringier-ad/index.html","searchKeys":["RingierAd"]},{"name":"ch.iagentur.ringieradsdk.external","description":null,"location":"ringieradsdk/ch.iagentur.ringieradsdk.external/index.html","searchKeys":["ch.iagentur.ringieradsdk.external"]},{"name":"AdController","description":null,"location":"ringieradsdk/ch.iagentur.ringieradsdk.external/-ad-controller/index.html","searchKeys":["AdController"]},{"name":"AdControllerListener","description":null,"location":"ringieradsdk/ch.iagentur.ringieradsdk.external/-ad-controller-listener/index.html","searchKeys":["AdControllerListener"]},{"name":"RingierConfig","description":null,"location":"ringieradsdk/ch.iagentur.ringieradsdk.external/-ringier-config/index.html","searchKeys":["RingierConfig"]},{"name":"ch.iagentur.ringieradsdk.external.ad","description":null,"location":"ringieradsdk/ch.iagentur.ringieradsdk.external.ad/index.html","searchKeys":["ch.iagentur.ringieradsdk.external.ad"]},{"name":"BannerAdView","description":null,"location":"ringieradsdk/ch.iagentur.ringieradsdk.external.ad/-banner-ad-view/index.html","searchKeys":["BannerAdView"]},{"name":"RingierAd","description":null,"location":"ringieradsdk/ch.iagentur.ringieradsdk.external.ad/-ringier-ad/index.html","searchKeys":["RingierAd"]},{"name":"RingierAdView","description":null,"location":"ringieradsdk/ch.iagentur.ringieradsdk.external.ad/-ringier-ad-view/index.html","searchKeys":["RingierAdView"]},{"name":"ch.iagentur.ringieradsdk.external.adadapters","description":null,"location":"ringieradsdk/ch.iagentur.ringieradsdk.external.adadapters/index.html","searchKeys":["ch.iagentur.ringieradsdk.external.adadapters"]},{"name":"AdAdapter","description":null,"location":"ringieradsdk/ch.iagentur.ringieradsdk.external.adadapters/-ad-adapter/index.html","searchKeys":["AdAdapter"]},{"name":"AdMobAdAdapter","description":null,"location":"ringieradsdk/ch.iagentur.ringieradsdk.external.adadapters/-ad-mob-ad-adapter/index.html","searchKeys":["AdMobAdAdapter"]},{"name":"XandrAdAdapter","description":null,"location":"ringieradsdk/ch.iagentur.ringieradsdk.external.adadapters/-xandr-ad-adapter/index.html","searchKeys":["XandrAdAdapter"]},{"name":"ch.iagentur.ringieradsdk.external.error","description":null,"location":"ringieradsdk/ch.iagentur.ringieradsdk.external.error/index.html","searchKeys":["ch.iagentur.ringieradsdk.external.error"]},{"name":"RingierAdError","description":null,"location":"ringieradsdk/ch.iagentur.ringieradsdk.external.error/-ringier-ad-error/index.html","searchKeys":["RingierAdError"]},{"name":"ch.iagentur.ringieradsdk.external.models","description":null,"location":"ringieradsdk/ch.iagentur.ringieradsdk.external.models/index.html","searchKeys":["ch.iagentur.ringieradsdk.external.models"]},{"name":"RingierAdSize","description":null,"location":"ringieradsdk/ch.iagentur.ringieradsdk.external.models/-ringier-ad-size/index.html","searchKeys":["RingierAdSize"]},{"name":"RingierAdUrlModel","description":null,"location":"ringieradsdk/ch.iagentur.ringieradsdk.external.models/-ringier-ad-url-model/index.html","searchKeys":["RingierAdUrlModel"]},{"name":"ch.iagentur.ringieradsdk.internal","description":null,"location":"ringieradsdk/ch.iagentur.ringieradsdk.internal/index.html","searchKeys":["ch.iagentur.ringieradsdk.internal"]},{"name":"AsyncManager","description":null,"location":"ringieradsdk/ch.iagentur.ringieradsdk.internal/-async-manager/index.html","searchKeys":["AsyncManager"]},{"name":"AsyncManagerImpl","description":null,"location":"ringieradsdk/ch.iagentur.ringieradsdk.internal/-async-manager-impl/index.html","searchKeys":["AsyncManagerImpl"]},{"name":"TagManagerConfigProvider","description":null,"location":"ringieradsdk/ch.iagentur.ringieradsdk.internal/-tag-manager-config-provider/index.html","searchKeys":["TagManagerConfigProvider"]},{"name":"TagManagerConfigProviderImpl","description":null,"location":"ringieradsdk/ch.iagentur.ringieradsdk.internal/-tag-manager-config-provider-impl/index.html","searchKeys":["TagManagerConfigProviderImpl"]},{"name":"ch.iagentur.ringieradsdk.internal.data.entities.models","description":null,"location":"ringieradsdk/ch.iagentur.ringieradsdk.internal.data.entities.models/index.html","searchKeys":["ch.iagentur.ringieradsdk.internal.data.entities.models"]},{"name":"AdParameters","description":null,"location":"ringieradsdk/ch.iagentur.ringieradsdk.internal.data.entities.models/-ad-parameters/index.html","searchKeys":["AdParameters"]},{"name":"ch.iagentur.ringieradsdk.internal.data.network.models","description":null,"location":"ringieradsdk/ch.iagentur.ringieradsdk.internal.data.network.models/index.html","searchKeys":["ch.iagentur.ringieradsdk.internal.data.network.models"]},{"name":"AdConfig","description":null,"location":"ringieradsdk/ch.iagentur.ringieradsdk.internal.data.network.models/-ad-config/index.html","searchKeys":["AdConfig"]},{"name":"AllowedSizes","description":null,"location":"ringieradsdk/ch.iagentur.ringieradsdk.internal.data.network.models/-allowed-sizes/index.html","searchKeys":["AllowedSizes"]},{"name":"LazyLoading","description":null,"location":"ringieradsdk/ch.iagentur.ringieradsdk.internal.data.network.models/-lazy-loading/index.html","searchKeys":["LazyLoading"]},{"name":"Modules","description":null,"location":"ringieradsdk/ch.iagentur.ringieradsdk.internal.data.network.models/-modules/index.html","searchKeys":["Modules"]},{"name":"Placements","description":null,"location":"ringieradsdk/ch.iagentur.ringieradsdk.internal.data.network.models/-placements/index.html","searchKeys":["Placements"]},{"name":"RootAd","description":null,"location":"ringieradsdk/ch.iagentur.ringieradsdk.internal.data.network.models/-root-ad/index.html","searchKeys":["RootAd"]},{"name":"SettingsGlobal","description":null,"location":"ringieradsdk/ch.iagentur.ringieradsdk.internal.data.network.models/-settings-global/index.html","searchKeys":["SettingsGlobal"]},{"name":"SettingsLocal","description":null,"location":"ringieradsdk/ch.iagentur.ringieradsdk.internal.data.network.models/-settings-local/index.html","searchKeys":["SettingsLocal"]},{"name":"SettingsModule","description":null,"location":"ringieradsdk/ch.iagentur.ringieradsdk.internal.data.network.models/-settings-module/index.html","searchKeys":["SettingsModule"]},{"name":"TargetingGlobal","description":null,"location":"ringieradsdk/ch.iagentur.ringieradsdk.internal.data.network.models/-targeting-global/index.html","searchKeys":["TargetingGlobal"]},{"name":"TargetingLocal","description":null,"location":"ringieradsdk/ch.iagentur.ringieradsdk.internal.data.network.models/-targeting-local/index.html","searchKeys":["TargetingLocal"]},{"name":"ch.iagentur.ringieradsdk.internal.extensions","description":null,"location":"ringieradsdk/ch.iagentur.ringieradsdk.internal.extensions/index.html","searchKeys":["ch.iagentur.ringieradsdk.internal.extensions"]},{"name":"asFloatPixels()","description":null,"location":"ringieradsdk/ch.iagentur.ringieradsdk.internal.extensions/as-float-pixels.html","searchKeys":["asFloatPixels()"]},{"name":"asIntPixels()","description":null,"location":"ringieradsdk/ch.iagentur.ringieradsdk.internal.extensions/as-int-pixels.html","searchKeys":["asIntPixels()"]},{"name":"dpsToFloatPixels()","description":null,"location":"ringieradsdk/ch.iagentur.ringieradsdk.internal.extensions/dps-to-float-pixels.html","searchKeys":["dpsToFloatPixels()"]},{"name":"dpsToIntPixels()","description":null,"location":"ringieradsdk/ch.iagentur.ringieradsdk.internal.extensions/dps-to-int-pixels.html","searchKeys":["dpsToIntPixels()"]},{"name":"getParentScrollView()","description":null,"location":"ringieradsdk/ch.iagentur.ringieradsdk.internal.extensions/get-parent-scroll-view.html","searchKeys":["getParentScrollView()"]},{"name":"isInScrollView()","description":null,"location":"ringieradsdk/ch.iagentur.ringieradsdk.internal.extensions/is-in-scroll-view.html","searchKeys":["isInScrollView()"]},{"name":"isIntInScreenWidth()","description":null,"location":"ringieradsdk/ch.iagentur.ringieradsdk.internal.extensions/is-int-in-screen-width.html","searchKeys":["isIntInScreenWidth()"]},{"name":"isViewVisibleInScrollView()","description":null,"location":"ringieradsdk/ch.iagentur.ringieradsdk.internal.extensions/is-view-visible-in-scroll-view.html","searchKeys":["isViewVisibleInScrollView()"]},{"name":"pixelsToFloatDps()","description":null,"location":"ringieradsdk/ch.iagentur.ringieradsdk.internal.extensions/pixels-to-float-dps.html","searchKeys":["pixelsToFloatDps()"]},{"name":"pixelsToIntDps()","description":null,"location":"ringieradsdk/ch.iagentur.ringieradsdk.internal.extensions/pixels-to-int-dps.html","searchKeys":["pixelsToIntDps()"]},{"name":"screenHeightAsIntDps()","description":null,"location":"ringieradsdk/ch.iagentur.ringieradsdk.internal.extensions/screen-height-as-int-dps.html","searchKeys":["screenHeightAsIntDps()"]},{"name":"screenWidthAsIntDps()","description":null,"location":"ringieradsdk/ch.iagentur.ringieradsdk.internal.extensions/screen-width-as-int-dps.html","searchKeys":["screenWidthAsIntDps()"]},{"name":"toMilliseconds()","description":null,"location":"ringieradsdk/ch.iagentur.ringieradsdk.internal.extensions/to-milliseconds.html","searchKeys":["toMilliseconds()"]},{"name":"toStringWithNewLine()","description":null,"location":"ringieradsdk/ch.iagentur.ringieradsdk.internal.extensions/to-string-with-new-line.html","searchKeys":["toStringWithNewLine()"]},{"name":"ch.iagentur.ringieradsdk.internal.utils","description":null,"location":"ringieradsdk/ch.iagentur.ringieradsdk.internal.utils/index.html","searchKeys":["ch.iagentur.ringieradsdk.internal.utils"]},{"name":"Logger","description":null,"location":"ringieradsdk/ch.iagentur.ringieradsdk.internal.utils/-logger/index.html","searchKeys":["Logger"]}]
